design.sv

module mux4to1_assign (
    input  wire [1:0] sel,
    input  wire [3:0] in,
    output wire       out
);
    assign out = (sel == 2'b00) ? in[0] :
                 (sel == 2'b01) ? in[1] :
                 (sel == 2'b10) ? in[2] :
                                 in[3];
endmodule

testbench.sv

module tb_mux4to1;

    reg [1:0] sel;
    reg [3:0] in;

    wire out_assign;
    wire out_case;
    wire out_if;

    mux4to1_assign mux_assign (
        .sel(sel),
        .in(in),
        .out(out_assign)
    );


    initial begin
      $dumpfile("mux4to1_assign.vcd");
      $dumpvars;
        $display("Time\tSel\tIn\tAssign\tCase\tIf");
        $monitor("%0t\t%02b\t%b\t%b\t%b\t%b", 
                  $time, sel, in, out_assign);

        in = 4'b1010;  

        sel = 2'b00; #10;
        sel = 2'b01; #10;
        sel = 2'b10; #10;
        sel = 2'b11; #10;

        in = 4'b0101;  
        sel = 2'b00; #10;
        sel = 2'b01; #10;
        sel = 2'b10; #10;
        sel = 2'b11; #10;

        $finish;
    end

endmodule

mux4to1_assign.vcd
$date
	Thu Aug  7 09:23:45 2025
$end
$version
	Icarus Verilog
$end
$timescale
	1s
$end
$scope module tb_mux4to1 $end
$var wire 1 ! out_assign $end
$var reg 4 " in [3:0] $end
$var reg 2 # sel [1:0] $end
$scope module mux_assign $end
$var wire 4 $ in [3:0] $end
$var wire 2 % sel [1:0] $end
$var wire 1 ! out $end
$upscope $end
$upscope $end
$enddefinitions $end
$comment Show the parameter values. $end
$dumpall
$end
#0
$dumpvars
b0 %
b1010 $
b0 #
b1010 "
0!
$end
#10
1!
b1 #
b1 %
#20
0!
b10 #
b10 %
#30
1!
b11 #
b11 %
#40
b0 #
b0 %
b101 "
b101 $
#50
0!
b1 #
b1 %
#60
1!
b10 #
b10 %
#70
0!
b11 #
b11 %
